twitter_generator/__init__.py
twitter_generator/exceptions.py
twitter_generator/version.py
twitter_generator/client_transaction/__init__.py
twitter_generator/client_transaction/main.py
twitter_generator/helpers/__init__.py
twitter_generator/helpers/cubic.py
twitter_generator/helpers/math_utils.py
twitter_generator/xp_forwarded_for/__init__.py
twitter_generator/xp_forwarded_for/main.py
twitter_generator-1.0.0.dist-info/licenses/LICENSE
twitter_generator-1.0.0.dist-info/METADATA
twitter_generator-1.0.0.dist-info/WHEEL
twitter_generator-1.0.0.dist-info/top_level.txt
twitter_generator-1.0.0.dist-info/RECORD
