Metadata-Version: 2.4
Name: twitter-generator
Version: 1.0.0
Summary: Python implementation for generating Twitter/X authentication headers (twitter-generator and X-XP-Forwarded-For)
Author-email: GlizzyKingDreko <glizzykingdreko@protonmail.com>
License: MIT
Project-URL: Homepage, https://github.com/GlizzyKingDreko/twitter-generator
Project-URL: Documentation, https://github.com/GlizzyKingDreko/twitter-generator/blob/main/LEARN.md
Project-URL: Repository, https://github.com/GlizzyKingDreko/twitter-generator
Project-URL: Issues, https://github.com/GlizzyKingDreko/twitter-generator/issues
Keywords: twitter,x,authentication,headers,client-transaction-id,xp-forwarded-for,reverse-engineering
Classifier: Development Status :: 4 - Beta
Classifier: Intended Audience :: Developers
Classifier: License :: OSI Approved :: MIT License
Classifier: Programming Language :: Python :: 3
Classifier: Programming Language :: Python :: 3.8
Classifier: Programming Language :: Python :: 3.9
Classifier: Programming Language :: Python :: 3.10
Classifier: Programming Language :: Python :: 3.11
Classifier: Programming Language :: Python :: 3.12
Classifier: Topic :: Internet :: WWW/HTTP
Classifier: Topic :: Security
Classifier: Topic :: Software Development :: Libraries :: Python Modules
Requires-Python: >=3.8
License-File: LICENSE
Requires-Dist: cryptography>=41.0.0
Requires-Dist: beautifulsoup4>=4.12.0
Provides-Extra: dev
Requires-Dist: pytest>=7.0.0; extra == "dev"
Requires-Dist: pytest-cov>=4.0.0; extra == "dev"
Requires-Dist: black>=23.0.0; extra == "dev"
Requires-Dist: flake8>=6.0.0; extra == "dev"
Requires-Dist: mypy>=1.0.0; extra == "dev"
Dynamic: license-file
